kd_med/__init__.py
kd_med/enc_plus_conv.py
kd_med/get_resnet3denc.py
kd_med/kd_loss.py
kd_med/pre_trained_enc.py
kd_med/resnet3denc.py
kd_med/unet3denc.py
tests/__init__.py
tests/runner.py
tests/test_EncPlusConvBase.py
tests/test_GetEncSConv.py
tests/test_PreTrainedEnc.py
tests/test_kd_loss.py
kd_med-0.0.12.dist-info/LICENSE
kd_med-0.0.12.dist-info/METADATA
kd_med-0.0.12.dist-info/WHEEL
kd_med-0.0.12.dist-info/top_level.txt
kd_med-0.0.12.dist-info/RECORD
