Metadata-Version: 2.1
Name: kd-med
Version: 0.0.12
Summary: A plug-in for knowledge distillation
Home-page: https://github.com/jingnan-jia/kd_med
Author: Jingnan
Author-email: jiajingnan2222@gmail.com
License: UNKNOWN
Platform: UNKNOWN
Classifier: Programming Language :: Python :: 3
Classifier: License :: OSI Approved :: MIT License
Classifier: Operating System :: OS Independent
Requires-Python: >=3.6
License-File: LICENSE
Requires-Dist: googledrivedownloader
Requires-Dist: torch
